MANIFEST.in
README.md
setup.py
easyleetcode/__init__.py
easyleetcode/config.py
easyleetcode.egg-info/PKG-INFO
easyleetcode.egg-info/SOURCES.txt
easyleetcode.egg-info/dependency_links.txt
easyleetcode.egg-info/requires.txt
easyleetcode.egg-info/top_level.txt
easyleetcode/leetcodes/JZoffer_001_变态跳台阶.py
easyleetcode/leetcodes/JZoffer_002_矩阵覆盖.py
easyleetcode/leetcodes/JZoffer_003_数值的整数次方.py
easyleetcode/leetcodes/JZoffer_004_链表中的倒数第K个节点.py
easyleetcode/leetcodes/JZoffer_005_树的子结构.py
easyleetcode/leetcodes/JZoffer_006_顺时针打印矩阵.py
easyleetcode/leetcodes/JZoffer_007_包含min函数的栈.py
easyleetcode/leetcodes/JZoffer_008_二叉搜索树的后序遍历序列.py
easyleetcode/leetcodes/JZoffer_009_二叉树中和为某一值的路径.py
easyleetcode/leetcodes/JZoffer_010_二叉搜索树与双向链表.py
easyleetcode/leetcodes/JZoffer_011_最小的K个数.py
easyleetcode/leetcodes/JZoffer_012_连续子数组的最大和.py
easyleetcode/leetcodes/JZoffer_013_从1到n的整数中1出现的个数.py
easyleetcode/leetcodes/JZoffer_014_把数组排成最小的数.py
easyleetcode/leetcodes/JZoffer_015_第一个只出现一次的字符.py
easyleetcode/leetcodes/JZoffer_016_数组中的逆序对.py
easyleetcode/leetcodes/JZoffer_017_统计一个数字在排序数组中的出现的次数.py
easyleetcode/leetcodes/JZoffer_018_和为S的连续正数序列.py
easyleetcode/leetcodes/JZoffer_019_和为S的两个数字.py
easyleetcode/leetcodes/JZoffer_020_扑克牌顺子.py
easyleetcode/leetcodes/JZoffer_021_孩子们的游戏（圆圈中最后剩下的数）.py
easyleetcode/leetcodes/JZoffer_022_求1+2+3+...+n.py
easyleetcode/leetcodes/JZoffer_023_把字符串转换成整数.py
easyleetcode/leetcodes/JZoffer_024_数组中重复的数字.py
easyleetcode/leetcodes/JZoffer_025_表示数值的字符串.py
easyleetcode/leetcodes/JZoffer_026_字符流中第一个不重复的字符.py
easyleetcode/leetcodes/JZoffer_027_二叉树的下一个结点.py
easyleetcode/leetcodes/JZoffer_028_二叉搜索树的第K个节点.py
easyleetcode/leetcodes/JZoffer_029_机器人的运动范围.py
easyleetcode/leetcodes/Leetcode_001_Two_Sum.py
easyleetcode/leetcodes/Leetcode_002_Add_Two_Numbers.py
easyleetcode/leetcodes/Leetcode_003_Longest_Substring_Without_Repeating_Characters.py
easyleetcode/leetcodes/Leetcode_004_Median of two Sorted Arrays.py
easyleetcode/leetcodes/Leetcode_005_Longest_Palindromic_Substring.py
easyleetcode/leetcodes/Leetcode_006_ZigZag_Conversion.py
easyleetcode/leetcodes/Leetcode_007_Reverse_Integer.py
easyleetcode/leetcodes/Leetcode_008_String_to_Integer(atoi).py
