Metadata-Version: 2.1
Name: easyleetcode
Version: 2.0.8
Summary: Leetcode easy study use Python on web
Home-page: https://github.com/425776024/easy_leetcode
Author: Jiang.XinFa
Author-email: 425776024@qq.com
License: MIT Licence
Keywords: easyleetcode,bilibili,youtube,leetcode
Platform: any
